types_workalendar-17.0.0.20250602.dist-info/licenses/LICENSE
workalendar-stubs/METADATA.toml
workalendar-stubs/__init__.pyi
workalendar-stubs/astronomy.pyi
workalendar-stubs/core.pyi
workalendar-stubs/exceptions.pyi
workalendar-stubs/precomputed_astronomy.pyi
workalendar-stubs/py.typed
workalendar-stubs/registry.pyi
workalendar-stubs/registry_tools.pyi
workalendar-stubs/skyfield_astronomy.pyi
workalendar-stubs/africa/__init__.pyi
workalendar-stubs/africa/algeria.pyi
workalendar-stubs/africa/angola.pyi
workalendar-stubs/africa/benin.pyi
workalendar-stubs/africa/ivory_coast.pyi
workalendar-stubs/africa/kenya.pyi
workalendar-stubs/africa/madagascar.pyi
workalendar-stubs/africa/mozambique.pyi
workalendar-stubs/africa/nigeria.pyi
workalendar-stubs/africa/sao_tome.pyi
workalendar-stubs/africa/south_africa.pyi
workalendar-stubs/africa/tunisia.pyi
workalendar-stubs/america/__init__.pyi
workalendar-stubs/america/argentina.pyi
workalendar-stubs/america/barbados.pyi
workalendar-stubs/america/brazil.pyi
workalendar-stubs/america/canada.pyi
workalendar-stubs/america/chile.pyi
workalendar-stubs/america/colombia.pyi
workalendar-stubs/america/el_salvador.pyi
workalendar-stubs/america/mexico.pyi
workalendar-stubs/america/panama.pyi
workalendar-stubs/america/paraguay.pyi
workalendar-stubs/asia/__init__.pyi
workalendar-stubs/asia/china.pyi
workalendar-stubs/asia/hong_kong.pyi
workalendar-stubs/asia/israel.pyi
workalendar-stubs/asia/japan.pyi
workalendar-stubs/asia/kazakhstan.pyi
workalendar-stubs/asia/malaysia.pyi
workalendar-stubs/asia/philippines.pyi
workalendar-stubs/asia/qatar.pyi
workalendar-stubs/asia/singapore.pyi
workalendar-stubs/asia/south_korea.pyi
workalendar-stubs/asia/taiwan.pyi
workalendar-stubs/europe/__init__.pyi
workalendar-stubs/europe/austria.pyi
workalendar-stubs/europe/belarus.pyi
workalendar-stubs/europe/belgium.pyi
workalendar-stubs/europe/bulgaria.pyi
workalendar-stubs/europe/cayman_islands.pyi
workalendar-stubs/europe/croatia.pyi
workalendar-stubs/europe/cyprus.pyi
workalendar-stubs/europe/czech_republic.pyi
types_workalendar-17.0.0.20250602.dist-info/METADATA
types_workalendar-17.0.0.20250602.dist-info/WHEEL
types_workalendar-17.0.0.20250602.dist-info/top_level.txt
types_workalendar-17.0.0.20250602.dist-info/RECORD
